agent_observability_langchain/__init__.py
agent_observability_langchain/tool.py
agent_observability_langchain-1.2.1.dist-info/licenses/LICENSE
tests/__init__.py
tests/test_tool.py
agent_observability_langchain-1.2.1.dist-info/METADATA
agent_observability_langchain-1.2.1.dist-info/WHEEL
agent_observability_langchain-1.2.1.dist-info/top_level.txt
agent_observability_langchain-1.2.1.dist-info/RECORD
