Metadata-Version: 2.4
Name: agent-observability-langchain
Version: 1.2.1
Summary: LangChain integration for Agent Observability - structured logging, cost tracking, and compliance for AI agents
Home-page: https://api-production-0c55.up.railway.app
Author: Agent Observability Team
Author-email: hello@agentobs.io
Project-URL: Homepage, https://api-production-0c55.up.railway.app
Project-URL: Documentation, https://api-production-0c55.up.railway.app/docs
Project-URL: Pricing, https://api-production-0c55.up.railway.app/pricing.json
Project-URL: OpenAPI, https://api-production-0c55.up.railway.app/openapi.json
Keywords: langchain,agent,observability,logging,compliance,audit,ai-agent,llm,cost-tracking,monitoring,analytics,structured-logging
Classifier: Development Status :: 4 - Beta
Classifier: Intended Audience :: Developers
Classifier: Topic :: Software Development :: Libraries :: Python Modules
Classifier: Topic :: System :: Monitoring
Classifier: Topic :: System :: Logging
Classifier: Topic :: Scientific/Engineering :: Artificial Intelligence
Classifier: License :: OSI Approved :: MIT License
Classifier: Programming Language :: Python :: 3
Classifier: Programming Language :: Python :: 3.9
Classifier: Programming Language :: Python :: 3.10
Classifier: Programming Language :: Python :: 3.11
Classifier: Programming Language :: Python :: 3.12
Classifier: Framework :: AsyncIO
Requires-Python: >=3.9
License-File: LICENSE
Requires-Dist: agent-observability>=1.1.0
Requires-Dist: langchain>=0.1.0
Requires-Dist: langchain-core>=0.1.0
Requires-Dist: pydantic>=2.0.0
Provides-Extra: dev
Requires-Dist: pytest>=7.0.0; extra == "dev"
Requires-Dist: pytest-asyncio>=0.21.0; extra == "dev"
Requires-Dist: black>=23.0.0; extra == "dev"
Requires-Dist: mypy>=1.0.0; extra == "dev"
Dynamic: author
Dynamic: author-email
Dynamic: classifier
Dynamic: description
Dynamic: description-content-type
Dynamic: home-page
Dynamic: keywords
Dynamic: license-file
Dynamic: project-url
Dynamic: provides-extra
Dynamic: requires-dist
Dynamic: requires-python
Dynamic: summary
